odoo/addons/l10n_ch_invoice_with_payment/README.rst
odoo/addons/l10n_ch_invoice_with_payment/__init__.py
odoo/addons/l10n_ch_invoice_with_payment/__manifest__.py
odoo/addons/l10n_ch_invoice_with_payment/data/report.xml
odoo/addons/l10n_ch_invoice_with_payment/i18n/l10n_ch_invoice_with_payment.pot
odoo/addons/l10n_ch_invoice_with_payment/models/__init__.py
odoo/addons/l10n_ch_invoice_with_payment/models/report.py
odoo/addons/l10n_ch_invoice_with_payment/readme/CONTRIBUTORS.rst
odoo/addons/l10n_ch_invoice_with_payment/readme/DESCRIPTION.rst
odoo/addons/l10n_ch_invoice_with_payment/readme/HISTORY.rst
odoo/addons/l10n_ch_invoice_with_payment/readme/USAGE.rst
odoo/addons/l10n_ch_invoice_with_payment/static/description/icon.png
odoo/addons/l10n_ch_invoice_with_payment/static/description/index.html
odoo11_addon_l10n_ch_invoice_with_payment-11.0.1.0.0.99.dev6.dist-info/METADATA
odoo11_addon_l10n_ch_invoice_with_payment-11.0.1.0.0.99.dev6.dist-info/WHEEL
odoo11_addon_l10n_ch_invoice_with_payment-11.0.1.0.0.99.dev6.dist-info/top_level.txt
odoo11_addon_l10n_ch_invoice_with_payment-11.0.1.0.0.99.dev6.dist-info/RECORD
